imatpy/__init__.py
imatpy/imat.py
imatpy/model_creation.py
imatpy/model_utils.py
imatpy/parse_gpr.py
imatpy-0.2.0.dist-info/METADATA
imatpy-0.2.0.dist-info/WHEEL
imatpy-0.2.0.dist-info/RECORD
