Metadata-Version: 2.4
Name: imatpy
Version: 0.2.0
Summary: Python implementation of the Integrative Metabolic Analysis Tool (iMAT) algorithm for context specific metabolic modeling.
Project-URL: homepage, https://github.com/Braden-Griebel/imatpy
Project-URL: repository, https://github.com/Braden-Griebel/imatpy
Project-URL: documentation, https://imatpy.readthedocs.io/en/stable/
Author-email: Braden Griebel <bgriebel@uw.edu>
License-Expression: MIT
Requires-Python: <3.13,>=3.9
Requires-Dist: cobra>=0.27.0
Requires-Dist: numpy>=1.26.0
Requires-Dist: optlang>=1.8.3
Requires-Dist: pandas>=2.0.0
Requires-Dist: scipy>=1.12.0
Requires-Dist: sympy>=1.12
Provides-Extra: cplex
Requires-Dist: cplex>=22.1.1.1; extra == 'cplex'
Provides-Extra: gurobipy
Requires-Dist: gurobipy>=11.0.0; extra == 'gurobipy'
